{"web":{"client_id":"72634954769-a83u9pdi2kuhn9qqdrslju70r0qpm1uh.apps.googleusercontent.com","project_id":"item-catalog-udacity-253318","auth_uri":"https://accounts.google.com/o/oauth2/auth","token_uri":"https://oauth2.googleapis.com/token","auth_provider_x509_cert_url":"https://www.googleapis.com/oauth2/v1/certs","redirect_uris":["http://localhost:5000","http://localhost:5000/login/callback","http://3.80.151.80.xip.io"],"javascript_origins":["http://localhost:5000","http://3.80.151.80.xip.io"]}}